puffyn/__init__.py
puffyn-0.0.0.dist-info/METADATA
puffyn-0.0.0.dist-info/WHEEL
puffyn-0.0.0.dist-info/top_level.txt
puffyn-0.0.0.dist-info/RECORD
