Metadata-Version: 2.1
Name: puffyn
Version: 0.0.0
Summary: soon ...
